[
  { "inputs": [], "stateMutability": "nonpayable", "type": "constructor" },
  {
    "anonymous": false,
    "inputs": [
      {
        "indexed": false,
        "internalType": "uint8",
        "name": "version",
        "type": "uint8"
      }
    ],
    "name": "Initialized",
    "type": "event"
  },
  {
    "anonymous": false,
    "inputs": [
      {
        "indexed": true,
        "internalType": "address",
        "name": "contributorAddress",
        "type": "address"
      },
      {
        "indexed": false,
        "internalType": "uint256",
        "name": "amount",
        "type": "uint256"
      },
      {
        "indexed": false,
        "internalType": "uint256",
        "name": "isShares",
        "type": "uint256"
      },
      {
        "indexed": false,
        "internalType": "address",
        "name": "baal",
        "type": "address"
      },
      {
        "indexed": false,
        "internalType": "address",
        "name": "vault",
        "type": "address"
      }
    ],
    "name": "ObReceived",
    "type": "event"
  },
  {
    "inputs": [],
    "name": "baal",
    "outputs": [
      { "internalType": "contract IBaal", "name": "", "type": "address" }
    ],
    "stateMutability": "view",
    "type": "function"
  },
  {
    "inputs": [],
    "name": "expiry",
    "outputs": [{ "internalType": "uint256", "name": "", "type": "uint256" }],
    "stateMutability": "view",
    "type": "function"
  },
  {
    "inputs": [
      { "internalType": "address", "name": "_moloch", "type": "address" },
      { "internalType": "address", "name": "_vault", "type": "address" },
      { "internalType": "uint256", "name": "_expiry", "type": "uint256" },
      { "internalType": "uint256", "name": "_multiply", "type": "uint256" },
      { "internalType": "uint256", "name": "_minTribute", "type": "uint256" },
      { "internalType": "bool", "name": "_isShares", "type": "bool" }
    ],
    "name": "init",
    "outputs": [],
    "stateMutability": "nonpayable",
    "type": "function"
  },
  {
    "inputs": [],
    "name": "isShares",
    "outputs": [{ "internalType": "bool", "name": "", "type": "bool" }],
    "stateMutability": "view",
    "type": "function"
  },
  {
    "inputs": [],
    "name": "minTribute",
    "outputs": [{ "internalType": "uint256", "name": "", "type": "uint256" }],
    "stateMutability": "view",
    "type": "function"
  },
  {
    "inputs": [],
    "name": "multiply",
    "outputs": [{ "internalType": "uint256", "name": "", "type": "uint256" }],
    "stateMutability": "view",
    "type": "function"
  },
  {
    "inputs": [],
    "name": "onboarder",
    "outputs": [],
    "stateMutability": "payable",
    "type": "function"
  },
  { "stateMutability": "payable", "type": "receive" }
]
